jupyter_pluto_proxy/__init__.py
jupyter_pluto_proxy/icons/pluto.svg
jupyter_pluto_proxy-0.1.2.dist-info/LICENSE
jupyter_pluto_proxy-0.1.2.dist-info/METADATA
jupyter_pluto_proxy-0.1.2.dist-info/WHEEL
jupyter_pluto_proxy-0.1.2.dist-info/entry_points.txt
jupyter_pluto_proxy-0.1.2.dist-info/top_level.txt
jupyter_pluto_proxy-0.1.2.dist-info/RECORD
