Metadata-Version: 2.1
Name: jupyter-pluto-proxy
Version: 0.1.2
Summary: Run Pluto.jl in JupyterHub
Home-page: https://github.com/yuvipanda/jupyter-pluto-proxy
Author: IllumiDesk Team & Yuvi Panda
Keywords: jupyter notebook,pluto notebook,jupyterhub,jupyterlab,jupyter-server-proxy
Classifier: Framework :: Jupyter
License-File: LICENSE
Requires-Dist: jupyter-server-proxy (>=1.5.0)
